rtl/imem/imem.v
module IMEM (
    input clk,                       // Clock signal
    input rst,                       // Reset signal
    input shift_enable,              // Shift enable signal
    input [15:0] new_value,          // New value to insert at IMEM[0]
    input [5:0] addr,                // 6-bit address to select a memory location
    output reg [15:0] data_out       // 16-bit data output
);

    // Define memory array: 64 words, each 16 bits wide
    reg [15:0] memory [0:63];
	integer i;

    // Reset and Shift Logic
    always @(posedge clk or posedge rst) begin
        if (rst) begin
            // Reset all memory values to 0
            
            for (i = 0; i < 64; i = i + 1) begin
                memory[i] <= 16'b0;
            end
        end else if (shift_enable) begin
            // Shift all memory values down

            for (i = 63; i > 0; i = i - 1) begin
                memory[i] <= memory[i-1];
            end
            // Insert the new value at IMEM[0]
            memory[0] <= new_value;
        end
    end

    // Read Logic
    always @(*) begin
        // Output the value at the specified address
        data_out = memory[addr];
    end

endmodule

qsim_rtl/imem/test_imem.v
module test_imem;

    // Inputs
    reg clk;
    reg rst;
    reg shift_enable;
    reg [15:0] new_value;
    reg [5:0] addr;

    // Output
    wire [15:0] data_out;

    // Instantiate the IMEM module
    IMEM uut (
        .clk(clk),
        .rst(rst),
        .shift_enable(shift_enable),
        .new_value(new_value),
        .addr(addr),
        .data_out(data_out)
    );

    // Clock generation
    initial begin
      $dumpfile("dump.vcd");
      $dumpvars(0, test_imem);

        clk = 0;
        forever #5 clk = ~clk; // 10 ns clock period
    end

    // Testbench logic
    initial begin
        // Initialize inputs
        rst = 1;
        shift_enable = 0;
        new_value = 16'h0000;
        addr = 6'b000000;

        // Release reset
        #10 rst = 0;

        // Insert new value at IMEM[0]
        #10 shift_enable = 1; new_value = 16'hAAAA;

        // Insert another value at IMEM[0], causing a shift
        #10 new_value = 16'hBBBB;

        // Insert another value at IMEM[0], causing another shift
        #10 new_value = 16'hCCCC;

        // Disable shift and read values from specific addresses
        #10 shift_enable = 0; addr = 6'd0; // Read IMEM[0]
        #10 addr = 6'd1;                   // Read IMEM[1]
        #10 addr = 6'd2;                   // Read IMEM[2]

        // End simulation
        #20 $finish;
    end

    // Monitor the output
    initial begin
        $monitor("Time: %t | Addr: %d | Data Out: %h", $time, addr, data_out);
    end

endmodule

qsim_rtl/imem/dump.vcd
$date
	Tue Dec 17 20:11:02 2024
$end
$version
	ModelSim Version 2024.2
$end
$timescale
	1ps
$end

$scope module test_imem $end
$var reg 1 ! clk $end
$var reg 1 " rst $end
$var reg 1 # shift_enable $end
$var reg 16 $ new_value [15:0] $end
$var reg 6 % addr [5:0] $end
$var wire 1 & data_out [15] $end
$var wire 1 ' data_out [14] $end
$var wire 1 ( data_out [13] $end
$var wire 1 ) data_out [12] $end
$var wire 1 * data_out [11] $end
$var wire 1 + data_out [10] $end
$var wire 1 , data_out [9] $end
$var wire 1 - data_out [8] $end
$var wire 1 . data_out [7] $end
$var wire 1 / data_out [6] $end
$var wire 1 0 data_out [5] $end
$var wire 1 1 data_out [4] $end
$var wire 1 2 data_out [3] $end
$var wire 1 3 data_out [2] $end
$var wire 1 4 data_out [1] $end
$var wire 1 5 data_out [0] $end

$scope module uut $end
$var wire 1 6 clk $end
$var wire 1 7 rst $end
$var wire 1 8 shift_enable $end
$var wire 1 9 new_value [15] $end
$var wire 1 : new_value [14] $end
$var wire 1 ; new_value [13] $end
$var wire 1 < new_value [12] $end
$var wire 1 = new_value [11] $end
$var wire 1 > new_value [10] $end
$var wire 1 ? new_value [9] $end
$var wire 1 @ new_value [8] $end
$var wire 1 A new_value [7] $end
$var wire 1 B new_value [6] $end
$var wire 1 C new_value [5] $end
$var wire 1 D new_value [4] $end
$var wire 1 E new_value [3] $end
$var wire 1 F new_value [2] $end
$var wire 1 G new_value [1] $end
$var wire 1 H new_value [0] $end
$var wire 1 I addr [5] $end
$var wire 1 J addr [4] $end
$var wire 1 K addr [3] $end
$var wire 1 L addr [2] $end
$var wire 1 M addr [1] $end
$var wire 1 N addr [0] $end
$var reg 16 O data_out [15:0] $end
$var integer 32 P i $end
$upscope $end
$upscope $end
$enddefinitions $end
#0
$dumpvars
0!
1"
0#
b0 $
b0 %
b0 O
b1000000 P
05
04
03
02
01
00
0/
0.
0-
0,
0+
0*
0)
0(
0'
0&
0N
0M
0L
0K
0J
0I
0H
0G
0F
0E
0D
0C
0B
0A
0@
0?
0>
0=
0<
0;
0:
09
08
17
06
$end
#5
1!
16
b0 P
b1 P
b10 P
b11 P
b100 P
b101 P
b110 P
b111 P
b1000 P
b1001 P
b1010 P
b1011 P
b1100 P
b1101 P
b1110 P
b1111 P
b10000 P
b10001 P
b10010 P
b10011 P
b10100 P
b10101 P
b10110 P
b10111 P
b11000 P
b11001 P
b11010 P
b11011 P
b11100 P
b11101 P
b11110 P
b11111 P
b100000 P
b100001 P
b100010 P
b100011 P
b100100 P
b100101 P
b100110 P
b100111 P
b101000 P
b101001 P
b101010 P
b101011 P
b101100 P
b101101 P
b101110 P
b101111 P
b110000 P
b110001 P
b110010 P
b110011 P
b110100 P
b110101 P
b110110 P
b110111 P
b111000 P
b111001 P
b111010 P
b111011 P
b111100 P
b111101 P
b111110 P
b111111 P
b1000000 P
#10
0"
0!
07
06
#15
1!
16
#20
1#
b1010101010101010 $
0!
18
1G
1E
1C
1A
1?
1=
1;
19
06
#25
1!
16
b111111 P
b111110 P
b111101 P
b111100 P
b111011 P
b111010 P
b111001 P
b111000 P
b110111 P
b110110 P
b110101 P
b110100 P
b110011 P
b110010 P
b110001 P
b110000 P
b101111 P
b101110 P
b101101 P
b101100 P
b101011 P
b101010 P
b101001 P
b101000 P
b100111 P
b100110 P
b100101 P
b100100 P
b100011 P
b100010 P
b100001 P
b100000 P
b11111 P
b11110 P
b11101 P
b11100 P
b11011 P
b11010 P
b11001 P
b11000 P
b10111 P
b10110 P
b10101 P
b10100 P
b10011 P
b10010 P
b10001 P
b10000 P
b1111 P
b1110 P
b1101 P
b1100 P
b1011 P
b1010 P
b1001 P
b1000 P
b111 P
b110 P
b101 P
b100 P
b11 P
b10 P
b1 P
b0 P
b1010101010101010 O
14
12
10
1.
1,
1*
1(
1&
#30
b1011101110111011 $
0!
1H
1D
1@
1<
06
#35
1!
16
b111111 P
b111110 P
b111101 P
b111100 P
b111011 P
b111010 P
b111001 P
b111000 P
b110111 P
b110110 P
b110101 P
b110100 P
b110011 P
b110010 P
b110001 P
b110000 P
b101111 P
b101110 P
b101101 P
b101100 P
b101011 P
b101010 P
b101001 P
b101000 P
b100111 P
b100110 P
b100101 P
b100100 P
b100011 P
b100010 P
b100001 P
b100000 P
b11111 P
b11110 P
b11101 P
b11100 P
b11011 P
b11010 P
b11001 P
b11000 P
b10111 P
b10110 P
b10101 P
b10100 P
b10011 P
b10010 P
b10001 P
b10000 P
b1111 P
b1110 P
b1101 P
b1100 P
b1011 P
b1010 P
b1001 P
b1000 P
b111 P
b110 P
b101 P
b100 P
b11 P
b10 P
b1 P
b0 P
b1011101110111011 O
15
11
1-
1)
#40
b1100110011001100 $
0!
0H
0G
1F
0D
0C
1B
0@
0?
1>
0<
0;
1:
06
#45
1!
16
b111111 P
b111110 P
b111101 P
b111100 P
b111011 P
b111010 P
b111001 P
b111000 P
b110111 P
b110110 P
b110101 P
b110100 P
b110011 P
b110010 P
b110001 P
b110000 P
b101111 P
b101110 P
b101101 P
b101100 P
b101011 P
b101010 P
b101001 P
b101000 P
b100111 P
b100110 P
b100101 P
b100100 P
b100011 P
b100010 P
b100001 P
b100000 P
b11111 P
b11110 P
b11101 P
b11100 P
b11011 P
b11010 P
b11001 P
b11000 P
b10111 P
b10110 P
b10101 P
b10100 P
b10011 P
b10010 P
b10001 P
b10000 P
b1111 P
b1110 P
b1101 P
b1100 P
b1011 P
b1010 P
b1001 P
b1000 P
b111 P
b110 P
b101 P
b100 P
b11 P
b10 P
b1 P
b0 P
b1100110011001100 O
05
04
13
01
00
1/
0-
0,
1+
0)
0(
1'
#50
0#
0!
08
06
#55
1!
16
#60
b1 %
0!
1N
06
b1011101110111011 O
15
14
03
11
10
0/
1-
1,
0+
1)
1(
0'
#65
1!
16
#70
b10 %
0!
0N
1M
06
b1010101010101010 O
05
01
0-
0)
